swin/__init__.py
swin/opts.py
swin/package.py
swin/swin.py
swin-0.0.5.dist-info/METADATA
swin-0.0.5.dist-info/WHEEL
swin-0.0.5.dist-info/entry_points.txt
swin-0.0.5.dist-info/licenses/LICENSE
swin-0.0.5.dist-info/RECORD
