Metadata-Version: 2.1
Name: swin
Version: 0.0.5
Summary: Swin: SoftWare INsights
Project-URL: Homepage, https://github.com/lunarserge/swin
Project-URL: Bug Tracker, https://github.com/lunarserge/swin/issues
Author: Serge Lunev
License-File: LICENSE
Classifier: License :: OSI Approved :: MIT License
Classifier: Operating System :: OS Independent
Classifier: Programming Language :: Python :: 3
Requires-Python: >=3.11
Requires-Dist: matplotlib>=3.7.1
Requires-Dist: numerize>=0.12
Requires-Dist: numpy>=1.24.2
Requires-Dist: pandas>=1.5.3
Requires-Dist: prettytable>=3.6.0
Requires-Dist: pypistats>=1.2.1
